CryptoDigital/__init__.py
CryptoDigital-0.0.2.dist-info/LICENSE
CryptoDigital-0.0.2.dist-info/METADATA
CryptoDigital-0.0.2.dist-info/WHEEL
CryptoDigital-0.0.2.dist-info/top_level.txt
CryptoDigital-0.0.2.dist-info/RECORD
