Metadata-Version: 2.1
Name: CryptoDigital
Version: 0.0.2
Summary: This is a library to get the online price of digital currencies.
Home-page: https://github.com/DrSudoSaeed
Author: SudoSaeed
Author-email: DrSudoSaeed@gmail.com
Project-URL: Bug Tracker, https://github.com/DrSudoSaeed/
Classifier: Programming Language :: Python :: 3
Classifier: License :: OSI Approved :: MIT License
Classifier: Operating System :: OS Independent
Requires-Python: >=3.6
License-File: LICENSE
